classr/__init__.py
classr-2.0.0.dist-info/LICENSE
classr-2.0.0.dist-info/WHEEL
classr-2.0.0.dist-info/METADATA
classr-2.0.0.dist-info/RECORD
